[
  {
    "op": "add",
    "path": "/spec/containers/0/command/-",
    "value": "--audit-policy-file=/etc/kubernetes/simple-policy.yaml"
  },
  {
    "op": "add",
    "path": "/spec/containers/0/command/-",
    "value": "--audit-log-path=/var/log/audit.log"
  },
  {
    "op": "add",
    "path": "/spec/containers/0/command/-",
    "value": "--audit-log-maxbackup=2"
  },
  {
    "op": "add",
    "path": "/spec/containers/0/command/-",
    "value": "--audit-log-maxage=7"
  },
  {
    "op": "add",
    "path": "/spec/containers/0/command/-",
    "value": "--audit-log-maxsize=200"
  }
]
